CHANGES.rst
CONTRIBUTORS.txt
LICENSE.txt
MANIFEST.in
README.rst
setup.py
dist/bst.pygasus.scaffolding-1.0.2.tar.gz
dist/bst.pygasus.scaffolding-1.0.2.tar.gz.asc
dist/bst.pygasus.scaffolding-1.0.tar.gz
dist/bst.pygasus.scaffolding-1.0.tar.gz.asc
src/bst/__init__.py
src/bst.pygasus.scaffolding.egg-info/PKG-INFO
src/bst.pygasus.scaffolding.egg-info/SOURCES.txt
src/bst.pygasus.scaffolding.egg-info/dependency_links.txt
src/bst.pygasus.scaffolding.egg-info/entry_points.txt
src/bst.pygasus.scaffolding.egg-info/namespace_packages.txt
src/bst.pygasus.scaffolding.egg-info/not-zip-safe
src/bst.pygasus.scaffolding.egg-info/requires.txt
src/bst.pygasus.scaffolding.egg-info/top_level.txt
src/bst/pygasus/__init__.py
src/bst/pygasus/scaffolding/__init__.py
src/bst/pygasus/scaffolding/configure.zcml
src/bst/pygasus/scaffolding/decorator.py
src/bst/pygasus/scaffolding/interfaces.py
src/bst/pygasus/scaffolding/mapping.py
src/bst/pygasus/scaffolding/recipe.py
src/bst/pygasus/scaffolding/scaffolding.py
src/bst/pygasus/scaffolding/fields/__init__.py
src/bst/pygasus/scaffolding/fields/column.py
src/bst/pygasus/scaffolding/fields/display.py
src/bst/pygasus/scaffolding/fields/editcolumn.py
src/bst/pygasus/scaffolding/fields/form.py
src/bst/pygasus/scaffolding/fields/model.py
src/bst/pygasus/scaffolding/templates/combobox.json.tpl
src/bst/pygasus/scaffolding/templates/combobox_renderer.json.tpl
src/bst/pygasus/scaffolding/templates/editgrid.json.tpl
src/bst/pygasus/scaffolding/templates/form.json.tpl
src/bst/pygasus/scaffolding/templates/grid.json.tpl
src/bst/pygasus/scaffolding/templates/store.json.tpl