Metadata-Version: 1.1
Name: bst.pygasus.scaffolding
Version: 1.0.2
Summary: provide form, grid, model, store generation for the bst.pygasus framework
Home-page: http://svn.plone.org/svn/collective/
Author: codeix
Author-email: samuel.riolo@biel-bienne.ch
License: ZPL 2.1
Keywords: pygasus web framework extjs
Platform: UNKNOWN
Classifier: Programming Language :: Python :: 3
Classifier: Natural Language :: English
Classifier: License :: OSI Approved :: Zope Public License
Classifier: Operating System :: OS Independent
Classifier: Development Status :: 4 - Beta
